README.md
setup.py
facectrl/__init__.py
facectrl/ctrl.py
facectrl/dataset.py
facectrl.egg-info/PKG-INFO
facectrl.egg-info/SOURCES.txt
facectrl.egg-info/dependency_links.txt
facectrl.egg-info/requires.txt
facectrl.egg-info/top_level.txt
facectrl/ml/__init__.py
facectrl/ml/classifier.py
facectrl/ml/detector.py
facectrl/ml/model.py
facectrl/ml/train.py
facectrl/video/__init__.py
facectrl/video/stream.py
facectrl/video/tracker.py