Metadata-Version: 2.1
Name: facectrl
Version: 0.0.1
Summary: FaceCTRL: control your media player with your face.
Home-page: https://github.com/galeone/facectrl
Author: Paolo Galeone
Author-email: me@pgaleone.eu
License: Mozilla Public License Version 2.0
Platform: UNKNOWN
Requires-Python: >=3.7
